srf_app_helper
