Metadata-Version: 1.1
Name: srf-app-helper
Version: 1.1.0
Summary: 为srf项目打造的app收集管理程序
Home-page: https://gitee.com/Wang_LaoSi/srf_app_helper
Author: WangLaoSi
Author-email: 103745315@qq.com
License: UNKNOWN
Download-URL: https://gitee.com/Wang_LaoSi/srf_app_helper/repository/archive/master.zip
Platform: UNKNOWN
